setup.py
kit/__init__.py
kit/credit_pay.py
kit/db/__init__.py
kit/db/db_helper.py
kit/dingding/__init__.py
kit/dingding/dding.py
kit/dingding/notify.py
kit/dingding/user.py
kit/util/__init__.py
kit/util/properties.py
mizlicai/__init__.py
mizlicai/mkit.py
mizlicai/model.py
mizlicai/product.py
mkit.egg-info/PKG-INFO
mkit.egg-info/SOURCES.txt
mkit.egg-info/dependency_links.txt
mkit.egg-info/entry_points.txt
mkit.egg-info/top_level.txt
sample/__init__.py
sample/db/__init__.py
sample/net/__init__.py
sample/net/request.py
test/__init__.py
test/credit_pay_test.py
test/test.py