Metadata-Version: 1.0
Name: mkit
Version: 1.13
Summary: 米庄理财小工具
Home-page: http://test.com
Author: qinchao
Author-email: qinchao@gmail.com
License: MIT Licence
Keywords: test,xxx
Platform: any
